[{"Description":"","EditedOn":"2025-03-02 18:30","LastAccessed":"2025-03-03 21:44","Filter":"{\"process\":[\"CHMCL-PH-FURN-FOL-Furn15\",\"AOTH-PET-_PET00\",\"C_EDU-SH_Boiler-FOL\",\"C_HLTH-PH_RH-ELC00\",\"ESOLPVBCOM20\",\"METAL-MoTP-Stat-ELC-Motor\",\"MINWODWST01\",\"MNNG-PH-STM_HW-NGA-Boiler\",\"MTHOL-FDSTCK-NGA-FDSTCK15\",\"PLPPPR-PH-STM_HW-FOL-Boiler\",\"R_DDW-SH_Burner-LPG00\",\"R_JDW-SH_RH-ELC\",\"R_DDW-SH_MSHP-ELC\",\"MINMNCWST00\",\"EWSTINC20\"],\"scenario\":[\"tui-v2_1_3\"],\"attribute\":[\"VAR_FOut\",\"VAR_FIn\",\"VAR_Act\"]}","Name":"flo_vs_act","UserName":"searlel"},{"Description":"","EditedOn":"2025-02-20 20:31","LastAccessed":"2025-02-20 20:31","Filter":"{\"userconstraint\":[\"WEM\"]}","Name":"wem","UserName":"searlel"},{"Description":"","EditedOn":"2025-02-18 02:07","LastAccessed":"2025-02-18 02:07","Filter":"{\"attribute\":[\"EQ_Peak\"]}","Name":"eq_peak","UserName":"searlel"},{"Description":"","EditedOn":"2025-01-15 23:23","LastAccessed":"2025-02-02 19:58","Filter":"{\"process\":[\"OTH-FOL-FOL-Tech\",\"OTH-FOL-FOL-Tech15\"],\"scenario\":[\"tui-v2_1_3\",\"tui-v2_1_3_iat\"],\"attribute\":[\"VAR_FOut\"]}","Name":"test_iat","UserName":"searlel"}]